rainbow/__init__.py
rainbow/main.py
rainbow_prompt-0.0.3.dist-info/LICENSE
rainbow_prompt-0.0.3.dist-info/METADATA
rainbow_prompt-0.0.3.dist-info/WHEEL
rainbow_prompt-0.0.3.dist-info/RECORD
