Metadata-Version: 2.1
Name: rainbow_prompt
Version: 0.0.3
Summary: This package aims to facilitate and simplify the use of colors in the prompt with python.
Author: David Marques
Author-email: davidmarques99@hotmail.com
Requires-Python: >=3.8,<4.0
Classifier: Programming Language :: Python :: 3
Classifier: Programming Language :: Python :: 3.8
Classifier: Programming Language :: Python :: 3.9
Classifier: Programming Language :: Python :: 3.10
Classifier: Programming Language :: Python :: 3.11
Classifier: Programming Language :: Python :: 3.12
